{
  "id": "md34",
  "label": "Spieltag 34",
  "date": "18.05.2013 - 18.05.2013",
  "no": 34,
  "matches": [
    {
      "id": "md34-01",
      "home": "Borussia Dortmund",
      "away": "TSG 1899 Hoffenheim",
      "homeTeam": "BVB",
      "awayTeam": "TSG",
      "result": "1:2",
      "date": "18.05.2013",
      "time": "15:30"
    },
    {
      "id": "md34-02",
      "home": "SC Freiburg",
      "away": "FC Schalke 04",
      "homeTeam": "SCF",
      "awayTeam": "S04",
      "result": "1:2",
      "date": "18.05.2013",
      "time": "15:30"
    },
    {
      "id": "md34-03",
      "home": "Hamburger SV",
      "away": "Bayer 04 Leverkusen",
      "homeTeam": "HSV",
      "awayTeam": "B04",
      "result": "0:1",
      "date": "18.05.2013",
      "time": "15:30"
    },
    {
      "id": "md34-04",
      "home": "VfB Stuttgart",
      "away": "FSV Mainz 05",
      "homeTeam": "VFB",
      "awayTeam": "M05",
      "result": "2:2",
      "date": "18.05.2013",
      "time": "15:30"
    },
    {
      "id": "md34-05",
      "home": "Hannover 96",
      "away": "Fortuna Düsseldorf",
      "homeTeam": "H96",
      "awayTeam": "F95",
      "result": "3:0",
      "date": "18.05.2013",
      "time": "15:30"
    },
    {
      "id": "md34-06",
      "home": "1. FC Nürnberg",
      "away": "SV Werder Bremen",
      "homeTeam": "FCN",
      "awayTeam": "SVW",
      "result": "3:2",
      "date": "18.05.2013",
      "time": "15:30"
    },
    {
      "id": "md34-07",
      "home": "Borussia Mönchengladbach",
      "away": "FC Bayern München",
      "homeTeam": "BMG",
      "awayTeam": "FCB",
      "result": "3:4",
      "date": "18.05.2013",
      "time": "15:30"
    },
    {
      "id": "md34-08",
      "home": "FC Augsburg",
      "away": "SpVgg Greuther Fürth",
      "homeTeam": "FCA",
      "awayTeam": "SGF",
      "result": "3:1",
      "date": "18.05.2013",
      "time": "15:30"
    },
    {
      "id": "md34-09",
      "home": "Eintracht Frankfurt",
      "away": "VfL Wolfsburg",
      "homeTeam": "SGE",
      "awayTeam": "WOB",
      "result": "2:2",
      "date": "18.05.2013",
      "time": "15:30"
    }
  ],
  "tips": [
    {
      "rank": 3,
      "player": "huy",
      "picks": {
        "md34-01": "3:0",
        "md34-02": "0:2",
        "md34-03": "1:2",
        "md34-04": "2:0",
        "md34-05": "3:2",
        "md34-06": "1:2",
        "md34-07": "1:4",
        "md34-08": "1:0",
        "md34-09": "2:1"
      },
      "pickPoints": {
        "md34-01": 0.0,
        "md34-02": 2.0,
        "md34-03": 3.0,
        "md34-04": 0.0,
        "md34-05": 2.0,
        "md34-06": 0.0,
        "md34-07": 2.0,
        "md34-08": 2.0,
        "md34-09": 0.0
      },
      "points": 11.0,
      "bonus": 0.0,
      "total": 408.0,
      "dayWin": false,
      "dayWinsTotal": 6.083333333333333
    },
    {
      "rank": 1,
      "player": "alois",
      "picks": {
        "md34-01": "1:0",
        "md34-02": "0:1",
        "md34-03": "0:1",
        "md34-04": "1:0",
        "md34-05": "1:0",
        "md34-06": "1:0",
        "md34-07": "0:1",
        "md34-08": "1:0",
        "md34-09": "1:0"
      },
      "pickPoints": {
        "md34-01": 0.0,
        "md34-02": 3.0,
        "md34-03": 4.0,
        "md34-04": 0.0,
        "md34-05": 2.0,
        "md34-06": 3.0,
        "md34-07": 3.0,
        "md34-08": 2.0,
        "md34-09": 0.0
      },
      "points": 17.0,
      "bonus": 3.0,
      "total": 410.0,
      "dayWin": true,
      "dayWinsTotal": 4.5
    },
    {
      "rank": 6,
      "player": "johannes",
      "picks": {
        "md34-01": "2:0",
        "md34-02": "1:1",
        "md34-03": "2:1",
        "md34-04": "1:0",
        "md34-05": "1:1",
        "md34-06": "1:1",
        "md34-07": "0:2",
        "md34-08": "2:1",
        "md34-09": "1:0"
      },
      "pickPoints": {
        "md34-01": 0.0,
        "md34-02": 0.0,
        "md34-03": 0.0,
        "md34-04": 0.0,
        "md34-05": 0.0,
        "md34-06": 0.0,
        "md34-07": 2.0,
        "md34-08": 2.0,
        "md34-09": 0.0
      },
      "points": 4.0,
      "bonus": 3.0,
      "total": 395.0,
      "dayWin": false,
      "dayWinsTotal": 7.166666666666666
    },
    {
      "rank": 5,
      "player": "kathi",
      "picks": {
        "md34-01": "3:1",
        "md34-02": "1:0",
        "md34-03": "0:2",
        "md34-04": "2:1",
        "md34-05": "1:0",
        "md34-06": "0:0",
        "md34-07": "0:3",
        "md34-08": "1:0",
        "md34-09": "1:0"
      },
      "pickPoints": {
        "md34-01": 0.0,
        "md34-02": 0.0,
        "md34-03": 2.0,
        "md34-04": 0.0,
        "md34-05": 2.0,
        "md34-06": 0.0,
        "md34-07": 2.0,
        "md34-08": 2.0,
        "md34-09": 0.0
      },
      "points": 8.0,
      "bonus": 3.0,
      "total": 398.0,
      "dayWin": false,
      "dayWinsTotal": 6.083333333333333
    },
    {
      "rank": 2,
      "player": "peter",
      "picks": {
        "md34-01": "3:1",
        "md34-02": "2:1",
        "md34-03": "1:2",
        "md34-04": "3:1",
        "md34-05": "2:0",
        "md34-06": "2:1",
        "md34-07": "1:4",
        "md34-08": "2:0",
        "md34-09": "3:1"
      },
      "pickPoints": {
        "md34-01": 0.0,
        "md34-02": 0.0,
        "md34-03": 3.0,
        "md34-04": 0.0,
        "md34-05": 2.0,
        "md34-06": 3.0,
        "md34-07": 2.0,
        "md34-08": 3.0,
        "md34-09": 0.0
      },
      "points": 13.0,
      "bonus": 3.0,
      "total": 400.0,
      "dayWin": false,
      "dayWinsTotal": 1.3333333333333333
    },
    {
      "rank": 3,
      "player": "thomas",
      "picks": {
        "md34-01": "4:1",
        "md34-02": "2:1",
        "md34-03": "1:2",
        "md34-04": "2:1",
        "md34-05": "2:2",
        "md34-06": "2:1",
        "md34-07": "0:3",
        "md34-08": "2:0",
        "md34-09": "2:1"
      },
      "pickPoints": {
        "md34-01": 0.0,
        "md34-02": 0.0,
        "md34-03": 3.0,
        "md34-04": 0.0,
        "md34-05": 0.0,
        "md34-06": 3.0,
        "md34-07": 2.0,
        "md34-08": 3.0,
        "md34-09": 0.0
      },
      "points": 11.0,
      "bonus": 3.0,
      "total": 387.0,
      "dayWin": false,
      "dayWinsTotal": 5.0
    },
    {
      "rank": 7,
      "player": "daniel",
      "picks": {
        "md34-01": null,
        "md34-02": null,
        "md34-03": null,
        "md34-04": null,
        "md34-05": null,
        "md34-06": null,
        "md34-07": null,
        "md34-08": null,
        "md34-09": null
      },
      "pickPoints": {
        "md34-01": 0.0,
        "md34-02": 0.0,
        "md34-03": 0.0,
        "md34-04": 0.0,
        "md34-05": 0.0,
        "md34-06": 0.0,
        "md34-07": 0.0,
        "md34-08": 0.0,
        "md34-09": 0.0
      },
      "points": 0.0,
      "bonus": 3.0,
      "total": 318.0,
      "dayWin": false,
      "dayWinsTotal": 2.0
    },
    {
      "rank": 7,
      "player": "nyclon",
      "picks": {
        "md34-01": null,
        "md34-02": null,
        "md34-03": null,
        "md34-04": null,
        "md34-05": null,
        "md34-06": null,
        "md34-07": null,
        "md34-08": null,
        "md34-09": null
      },
      "pickPoints": {
        "md34-01": 0.0,
        "md34-02": 0.0,
        "md34-03": 0.0,
        "md34-04": 0.0,
        "md34-05": 0.0,
        "md34-06": 0.0,
        "md34-07": 0.0,
        "md34-08": 0.0,
        "md34-09": 0.0
      },
      "points": 0.0,
      "bonus": 0.0,
      "total": 271.0,
      "dayWin": false,
      "dayWinsTotal": 1.5833333333333333
    },
    {
      "rank": 7,
      "player": "melli",
      "picks": {
        "md34-01": null,
        "md34-02": null,
        "md34-03": null,
        "md34-04": null,
        "md34-05": null,
        "md34-06": null,
        "md34-07": null,
        "md34-08": null,
        "md34-09": null
      },
      "pickPoints": {
        "md34-01": 0.0,
        "md34-02": 0.0,
        "md34-03": 0.0,
        "md34-04": 0.0,
        "md34-05": 0.0,
        "md34-06": 0.0,
        "md34-07": 0.0,
        "md34-08": 0.0,
        "md34-09": 0.0
      },
      "points": 0.0,
      "bonus": 3.0,
      "total": 58.0,
      "dayWin": false,
      "dayWinsTotal": 0.25
    },
    {
      "rank": 7,
      "player": "manu",
      "picks": {
        "md34-01": null,
        "md34-02": null,
        "md34-03": null,
        "md34-04": null,
        "md34-05": null,
        "md34-06": null,
        "md34-07": null,
        "md34-08": null,
        "md34-09": null
      },
      "pickPoints": {
        "md34-01": 0.0,
        "md34-02": 0.0,
        "md34-03": 0.0,
        "md34-04": 0.0,
        "md34-05": 0.0,
        "md34-06": 0.0,
        "md34-07": 0.0,
        "md34-08": 0.0,
        "md34-09": 0.0
      },
      "points": 0.0,
      "bonus": 0.0,
      "total": 11.0,
      "dayWin": false,
      "dayWinsTotal": 0.0
    },
    {
      "rank": 7,
      "player": "markus",
      "picks": {
        "md34-01": null,
        "md34-02": null,
        "md34-03": null,
        "md34-04": null,
        "md34-05": null,
        "md34-06": null,
        "md34-07": null,
        "md34-08": null,
        "md34-09": null
      },
      "pickPoints": {
        "md34-01": 0.0,
        "md34-02": 0.0,
        "md34-03": 0.0,
        "md34-04": 0.0,
        "md34-05": 0.0,
        "md34-06": 0.0,
        "md34-07": 0.0,
        "md34-08": 0.0,
        "md34-09": 0.0
      },
      "points": 0.0,
      "bonus": 0.0,
      "total": 10.0,
      "dayWin": false,
      "dayWinsTotal": 0.0
    }
  ],
  "table": [
    {
      "rank": 2,
      "player": "huy",
      "points": 11.0,
      "bonus": 0.0,
      "total": 408.0,
      "dayWinsTotal": 6.083333333333333
    },
    {
      "rank": 1,
      "player": "alois",
      "points": 17.0,
      "bonus": 3.0,
      "total": 410.0,
      "dayWinsTotal": 4.5
    },
    {
      "rank": 5,
      "player": "johannes",
      "points": 4.0,
      "bonus": 3.0,
      "total": 395.0,
      "dayWinsTotal": 7.166666666666666
    },
    {
      "rank": 4,
      "player": "kathi",
      "points": 8.0,
      "bonus": 3.0,
      "total": 398.0,
      "dayWinsTotal": 6.083333333333333
    },
    {
      "rank": 3,
      "player": "peter",
      "points": 13.0,
      "bonus": 3.0,
      "total": 400.0,
      "dayWinsTotal": 1.3333333333333333
    },
    {
      "rank": 6,
      "player": "thomas",
      "points": 11.0,
      "bonus": 3.0,
      "total": 387.0,
      "dayWinsTotal": 5.0
    },
    {
      "rank": 7,
      "player": "daniel",
      "points": 0.0,
      "bonus": 3.0,
      "total": 318.0,
      "dayWinsTotal": 2.0
    },
    {
      "rank": 8,
      "player": "nyclon",
      "points": 0.0,
      "bonus": 0.0,
      "total": 271.0,
      "dayWinsTotal": 1.5833333333333333
    },
    {
      "rank": 9,
      "player": "melli",
      "points": 0.0,
      "bonus": 3.0,
      "total": 58.0,
      "dayWinsTotal": 0.25
    },
    {
      "rank": 10,
      "player": "manu",
      "points": 0.0,
      "bonus": 0.0,
      "total": 11.0,
      "dayWinsTotal": 0.0
    },
    {
      "rank": 11,
      "player": "markus",
      "points": 0.0,
      "bonus": 0.0,
      "total": 10.0,
      "dayWinsTotal": 0.0
    },
    {
      "rank": 12,
      "player": "denis",
      "points": 0.0,
      "bonus": 0.0,
      "total": 0.0,
      "dayWinsTotal": 0.0
    },
    {
      "rank": 12,
      "player": "bernhard",
      "points": 0.0,
      "bonus": 0.0,
      "total": 0.0,
      "dayWinsTotal": 0.0
    },
    {
      "rank": 12,
      "player": "franzi",
      "points": 0.0,
      "bonus": 0.0,
      "total": 0.0,
      "dayWinsTotal": 0.0
    }
  ]
}